README.rst
setup.py
modman/__init__.py
modman/api.py
modman/util.py
modman.egg-info/PKG-INFO
modman.egg-info/SOURCES.txt
modman.egg-info/dependency_links.txt
modman.egg-info/entry_points.txt
modman.egg-info/not-zip-safe
modman.egg-info/requires.txt
modman.egg-info/top_level.txt
modman/contrib/__init__.py
modman/contrib/simutrans.py