Metadata-Version: 1.0
Name: modman
Version: 1
Summary: Tool for managing game mods
Home-page: https://github.com/ojii/modman
Author: Jonas Obrist
Author-email: ojiidotch@gmail.com
License: BSD License
Platform: OS Independent
